[{"CreationDate":"2026-03-05T09:41:06.7020308-05:00","Comment":"","UserId":1,"Action":"Logout","Id":1},{"CreationDate":"2026-03-05T09:49:20.8234172-05:00","Comment":"","UserId":1,"Action":"Login","Id":2},{"CreationDate":"2026-03-05T09:49:46.6544013-05:00","Comment":"","UserId":1,"Action":"Expired/blocked","Id":3},{"CreationDate":"2026-03-05T09:50:55.5505753-05:00","Comment":"","UserId":1,"Action":"Login","Id":4},{"CreationDate":"2026-03-05T09:53:01.3454198-05:00","Comment":"","UserId":1,"Action":"Expired/blocked","Id":5},{"CreationDate":"2026-03-05T09:54:05.8461409-05:00","Comment":"","UserId":1,"Action":"Login","Id":6},{"CreationDate":"2026-03-05T09:57:45.8725798-05:00","Comment":"","UserId":2,"Action":"Subscribe","Id":7},{"CreationDate":"2026-03-05T09:58:24.5236595-05:00","Comment":"","UserId":1,"Action":"Login","Id":8},{"CreationDate":"2026-03-05T09:58:29.1726239-05:00","Comment":"","UserId":1,"Action":"ManageUsers","Id":9},{"CreationDate":"2026-03-05T09:58:51.9874359-05:00","Comment":"","UserId":2,"Action":"Login","Id":10},{"CreationDate":"2026-03-05T09:59:24.7626871-05:00","Comment":"","UserId":2,"Action":"Logout","Id":11},{"CreationDate":"2026-03-05T10:00:23.3616039-05:00","Comment":"","UserId":1,"Action":"Logout","Id":12},{"CreationDate":"2026-03-14T09:40:28.1902305-04:00","Comment":"","UserId":1,"Action":"Login","Id":13},{"CreationDate":"2026-03-14T09:41:33.6947688-04:00","Comment":"","UserId":1,"Action":"Logout","Id":14},{"CreationDate":"2026-03-14T09:51:13.9677929-04:00","Comment":"","UserId":1,"Action":"Login","Id":15},{"CreationDate":"2026-03-14T09:51:49.1860449-04:00","Comment":"","UserId":1,"Action":"Login","Id":16},{"CreationDate":"2026-03-14T10:03:47.3397824-04:00","Comment":"","UserId":1,"Action":"ManageUsers","Id":17},{"CreationDate":"2026-03-14T10:07:34.475755-04:00","Comment":"","UserId":1,"Action":"ManageUsers","Id":18},{"CreationDate":"2026-03-14T10:09:38.045101-04:00","Comment":"","UserId":1,"Action":"ManageUsers","Id":19},{"CreationDate":"2026-03-14T10:10:56.2447046-04:00","Comment":"","UserId":1,"Action":"Logout","Id":20},{"CreationDate":"2026-03-14T10:21:14.4732028-04:00","Comment":"","UserId":1,"Action":"Login","Id":21},{"CreationDate":"2026-03-14T10:21:29.6021526-04:00","Comment":"","UserId":1,"Action":"Logout","Id":22},{"CreationDate":"2026-03-14T10:22:40.9205044-04:00","Comment":"","UserId":1,"Action":"Login","Id":23},{"CreationDate":"2026-03-14T10:22:46.8539169-04:00","Comment":"","UserId":1,"Action":"ManageUsers","Id":24},{"CreationDate":"2026-03-14T10:23:26.0846512-04:00","Comment":"","UserId":2,"Action":"Login","Id":25},{"CreationDate":"2026-03-14T10:23:34.8795148-04:00","Comment":"","UserId":1,"Action":"ManageUsers","Id":26},{"CreationDate":"2026-03-14T10:23:56.5280476-04:00","Comment":"","UserId":1,"Action":"ManageUsers","Id":27},{"CreationDate":"2026-03-14T10:34:15.5408555-04:00","Comment":"","UserId":1,"Action":"Logout","Id":28},{"CreationDate":"2026-03-14T10:34:18.9478924-04:00","Comment":"","UserId":2,"Action":"Logout","Id":29},{"CreationDate":"2026-03-15T14:06:11.1104723-04:00","Comment":"","UserId":2,"Action":"Login","Id":30},{"CreationDate":"2026-03-15T14:07:10.4410287-04:00","Comment":"","UserId":2,"Action":"Logout","Id":31},{"CreationDate":"2026-03-15T14:07:31.31159-04:00","Comment":"","UserId":1,"Action":"Login","Id":32},{"CreationDate":"2026-03-15T14:07:35.5534797-04:00","Comment":"","UserId":1,"Action":"ManageUsers","Id":33},{"CreationDate":"2026-03-15T14:07:53.4085833-04:00","Comment":"","UserId":1,"Action":"Logout","Id":34},{"CreationDate":"2026-03-15T16:12:01.4004508-04:00","Comment":"","UserId":1,"Action":"Login","Id":35},{"CreationDate":"2026-03-15T16:15:44.2568518-04:00","Comment":"","UserId":1,"Action":"Logout","Id":36},{"CreationDate":"2026-03-15T16:26:56.5076007-04:00","Comment":"","UserId":10,"Action":"Login","Id":37},{"CreationDate":"2026-03-15T16:34:13.0403258-04:00","Comment":"","UserId":11,"Action":"Login","Id":38},{"CreationDate":"2026-03-15T16:38:47.7874441-04:00","Comment":"","UserId":11,"Action":"Logout","Id":39},{"CreationDate":"2026-03-15T16:38:51.4692866-04:00","Comment":"","UserId":10,"Action":"Logout","Id":40},{"CreationDate":"2026-03-15T16:41:03.9536693-04:00","Comment":"","UserId":10,"Action":"Login","Id":41},{"CreationDate":"2026-03-15T16:41:12.6929824-04:00","Comment":"","UserId":11,"Action":"Login","Id":42},{"CreationDate":"2026-03-15T16:50:00.9382121-04:00","Comment":"","UserId":10,"Action":"Logout","Id":43},{"CreationDate":"2026-03-15T17:04:49.6651741-04:00","Comment":"","UserId":10,"Action":"Login","Id":44},{"CreationDate":"2026-03-15T17:04:56.5871757-04:00","Comment":"","UserId":11,"Action":"Login","Id":45},{"CreationDate":"2026-03-15T17:07:15.0387134-04:00","Comment":"","UserId":10,"Action":"Logout","Id":46},{"CreationDate":"2026-03-15T17:10:51.7171182-04:00","Comment":"","UserId":10,"Action":"Login","Id":47},{"CreationDate":"2026-03-15T17:10:55.2922055-04:00","Comment":"","UserId":11,"Action":"Login","Id":48},{"CreationDate":"2026-03-15T17:13:03.6866654-04:00","Comment":"","UserId":10,"Action":"Logout","Id":49},{"CreationDate":"2026-03-15T17:13:05.6290748-04:00","Comment":"","UserId":11,"Action":"Logout","Id":50},{"CreationDate":"2026-03-21T08:59:49.6123923-04:00","Comment":"","UserId":1,"Action":"Login","Id":51},{"CreationDate":"2026-03-21T09:00:02.3626191-04:00","Comment":"","UserId":2,"Action":"Login","Id":52},{"CreationDate":"2026-03-21T09:00:49.7698473-04:00","Comment":"asd","UserId":1,"Action":"Create","Id":53},{"CreationDate":"2026-03-21T09:10:24.6645549-04:00","Comment":"","UserId":1,"Action":"Login","Id":54},{"CreationDate":"2026-03-21T09:10:44.2951003-04:00","Comment":"asd","UserId":1,"Action":"Create","Id":55},{"CreationDate":"2026-03-21T09:10:48.7231627-04:00","Comment":"","UserId":2,"Action":"Login","Id":56},{"CreationDate":"2026-03-21T09:11:57.9041554-04:00","Comment":"","UserId":1,"Action":"ManageUsers","Id":57},{"CreationDate":"2026-03-21T09:12:02.0635077-04:00","Comment":"","UserId":1,"Action":"SetUserAccess","Id":58},{"CreationDate":"2026-03-21T09:12:08.7000202-04:00","Comment":"","UserId":1,"Action":"Expired/blocked","Id":59},{"CreationDate":"2026-03-21T09:12:30.9350879-04:00","Comment":"","UserId":1,"Action":"Login","Id":60},{"CreationDate":"2026-03-21T09:13:19.9482062-04:00","Comment":"","UserId":2,"Action":"Expired/blocked","Id":61},{"CreationDate":"2026-03-21T09:14:12.9540607-04:00","Comment":"","UserId":2,"Action":"Login","Id":62},{"CreationDate":"2026-03-21T09:14:34.170052-04:00","Comment":"","UserId":1,"Action":"Logout","Id":63},{"CreationDate":"2026-03-21T09:14:36.6626956-04:00","Comment":"","UserId":2,"Action":"Logout","Id":64}]
